cxr_foundation/__init__.py
cxr_foundation/constants.py
cxr_foundation/example_generator_lib.py
cxr_foundation/example_generator_lib_test.py
cxr_foundation/inference_beam_lib.py
cxr_foundation/inference_beam_lib_test.py
cxr_foundation/run_inference.py
cxr_foundation/train.py
cxr_foundation/train_lib.py
cxr_foundation/train_lib_test.py
cxr_foundation-0.0.14.dist-info/LICENSE
cxr_foundation-0.0.14.dist-info/METADATA
cxr_foundation-0.0.14.dist-info/WHEEL
cxr_foundation-0.0.14.dist-info/top_level.txt
cxr_foundation-0.0.14.dist-info/RECORD
