Metadata-Version: 2.1
Name: cxr-foundation
Version: 0.0.14
Summary: CXR Foundation: chest x-ray embeddings generation.
Home-page: UNKNOWN
Author: UNKNOWN
Author-email: UNKNOWN
License: UNKNOWN
Platform: UNKNOWN
Requires-Dist: google-api-python-client
Requires-Dist: google-apitools
Requires-Dist: google-cloud-aiplatform
Requires-Dist: google-cloud-storage
Requires-Dist: apache-beam
Requires-Dist: pandas
Requires-Dist: tensorflow (>=2.10.0)
Requires-Dist: pillow
Requires-Dist: pypng
Requires-Dist: pydicom
Requires-Dist: tf-models-official (>=2.10.0)
Requires-Dist: protobuf (<3.20)
Requires-Dist: typing-extensions
Requires-Dist: shapely (<2.0.0)
